{
  "id": "product_258",
  "title": "RGB Crystal Touch Table Lamp, LED Night Light Bedside Lamp with USB Charging Port for Living Room Bedroom",
  "description": "3 Modes 16 Color Changing LampAcrylic Material decorative crystal table lampPortable Cordless Lights2 Hour Fast USB Charging Time8-12 Hour working timeExquisite Gifts and Small Lamp DecorationsWith Box Packing",
  "availability": "in stock",
  "condition": "new",
  "price": 1430,
  "link": "",
  "image_link1": "https://hhcnewapp.blr1.digitaloceanspaces.com/uploads/2024/03/YA12-7.jpg",
  "image_link2": "https://hhcnewapp.blr1.digitaloceanspaces.com/uploads/2024/03/YA12-M.jpg",
  "image_link3": "https://hhcnewapp.blr1.digitaloceanspaces.com/uploads/2024/03/YA12-1.jpg",
  "image_link4": "https://hhcnewapp.blr1.digitaloceanspaces.com/uploads/2024/03/YA12-6-504x504-1.jpg",
  "image_link5": "",
  "image_link6": "",
  "image_link7": "",
  "image_link8": "",
  "image_link9": "",
  "image_link10": "",
  "image_link11": "",
  "image_link12": "",
  "image_link13": "",
  "image_link14": "",
  "image_link15": "",
  "category": "TVs & Home Appliances",
  "subcategory": "Home_Appliances",
  "product_tags": "Women's_Clothing",
  "product_url": "products/product_258/rgb-crystal-touch-table-lamp-led-night-light-bedside-lamp-with-usb-charging-port-for-living-room-bedroom.json",
  "category_url": "categories/tvs-home-appliances.json",
  "subcategory_url": "categories/tvs-home-appliances/home-appliances.json"
}